src/__init__.py
src/app.py
src/core/__init__.py
src/core/base.py
src/core/eml.py
src/core/parse_tab.py
src/core/store.py
src/core/util.py
src/db/.gitkeep
src/runner.py
src/storage/output/.gitkeep
src/storage/source/emails/.gitkeep
emreader-0.1.9.dist-info/METADATA
emreader-0.1.9.dist-info/WHEEL
emreader-0.1.9.dist-info/entry_points.txt
emreader-0.1.9.dist-info/RECORD
